{
 "AccountFormController": 2,
 "Account": 5,
 "AccountForm": 5,
 "AccountValidator": 5,
 "PetStoreImpl": 7,
 "UserSession": 5,
 "AddItemToCartController": 7,
 "Cart": 2,
 "CartItem": 2,
 "Item": 7,
 "Category": 10,
 "LineItem": 2,
 "Order": 2,
 "OrderFormController": 5,
 "OrderForm": 8,
 "OrderValidator": 2,
 "SqlMapAccountDao": 5,
 "SqlMapCategoryDao": 10,
 "SqlMapItemDao": 7,
 "SqlMapOrderDao": 2,
 "SqlMapProductDao": 7,
 "RemoveItemFromCartController": 3,
 "ListOrdersController": 0,
 "Product": 7,
 "SearchProductsController": 7,
 "SignoffController": 1,
 "SignonController": 7,
 "SignonInterceptor": 5,
 "UpdateCartQuantitiesController": 9,
 "ViewCartController": 9,
 "ViewCategoryController": 7,
 "ViewItemController": 7,
 "ViewOrderController": 0,
 "ViewProductController": 7,
 "SqlMapSequenceDao": 6,
 "SqlMapProductDao::ProductSearch": 4,
 "Sequence": 6
}